[
  {
    "id": "pfbid0gc9SvotWCUupVcaGuoJquyYtPTkvN1wPsynyWi1G8bre5yd2Wg6xq8VJHVUd7CWbl",
    "url": "https://www.facebook.com/PhongTroBinhThanh/posts/pfbid0gc9SvotWCUupVcaGuoJquyYtPTkvN1wPsynyWi1G8bre5yd2Wg6xq8VJHVUd7CWbl",
    "content": " Ung Văn Khiêm- Bình Thạnh đang trống phòngNhà trống sẵnCó thang máyCho nuôi pet- Điện 4k, nước 100k/ng, phí dv 150k/tháng- Giặt phơi  __________________________Khách em có nhu cầu xem phòng  0377870876",
    "price": "",
    "address": "Ung Văn Khiêm, Bình Thạnh",
    "contact": "0377870876"
  },
  {
    "id": "1318896355683214",
    "url": "https://www.facebook.com/PhongTroBinhThanh/videos/1318896355683214/",
    "content": " PHÒNG TRỐNG CÓ THỂ DỌN VÀO Ở NGAY  Mặt tiền đường dễ di chuyển  - 758 Xô Viết Nghệ Tĩnh Cách HUTECH cơ sở Ung Văn Khiêm khoảng 500m Sẵn giường, nệm, tủ, máy lạnh, tủ lạnh, kệ bếp, máy giặt, bàn ghế... Chỉ 5tr/tháng Call/Zalo chủ nhà: 094.593.3579 - Huy (1984)",
    "price": "5tr/tháng",
    "address": "758 Xô Viết Nghệ Tĩnh",
    "contact": {
      "phone": "094.593.3579",
      "name": "Huy",
      "year_of_birth": "1984"
    }
  },
  {
    "id": "pfbid02NqkLhR4jbgtNSqfrEFxczocw61VQd6xAGBFE7WEUfihmUHJqBrx28dS8eJA7ZE6Vl",
    "url": "https://www.facebook.com/PhongTroBinhThanh/posts/pfbid02NqkLhR4jbgtNSqfrEFxczocw61VQd6xAGBFE7WEUfihmUHJqBrx28dS8eJA7ZE6Vl",
    "content": " PHÒNG NHƯ HÌNH, CÓ THỂ DỌN VÀO Ở NGAY  758 Xô Viết Nghệ Tĩnh Mặt tiền đường dễ di chuyển  Cách ĐH HUTECH cơ sở Ung Văn Khiêm khoảng 500m Sẵn giường, nệm, tủ, máy lạnh, tủ lạnh, kệ bếp, máy giặt, bàn ghế... Chỉ 5tr/tháng Call/Zalo chủ nhà: 094.593.3579 - Huy (1984)",
    "price": "5tr/tháng",
    "address": "758 Xô Viết Nghệ Tĩnh",
    "contact": {
      "phone": "094.593.3579",
      "name": "Huy",
      "year_of_birth": "1984"
    }
  }
]
